[
    {
        "status": "completed", 
        "check_run_url": "https://api.github.com/repos/cpp-pm/hunter/check-runs/1407196179", 
        "name": "filament clang-libcxx17-fpic ubuntu-20.04", 
        "run_id": 362807396, 
        "url": "https://api.github.com/repos/cpp-pm/hunter/actions/jobs/1407196179", 
        "html_url": "https://github.com/cpp-pm/hunter/runs/1407196179", 
        "completed_at": "2020-11-16T15:45:35Z", 
        "run_url": "https://api.github.com/repos/cpp-pm/hunter/actions/runs/362807396", 
        "node_id": "MDg6Q2hlY2tSdW4xNDA3MTk2MTc5", 
        "steps": [
            {
                "status": "completed", 
                "name": "Set up job", 
                "number": 1, 
                "completed_at": "2020-11-16T15:38:56.000Z", 
                "started_at": "2020-11-16T15:38:53.000Z", 
                "conclusion": "success"
            }, 
            {
                "status": "completed", 
                "name": "Git checkout with submodules", 
                "number": 2, 
                "completed_at": "2020-11-16T15:39:00.000Z", 
                "started_at": "2020-11-16T15:38:56.000Z", 
                "conclusion": "success"
            }, 
            {
                "status": "completed", 
                "name": "Set up Python", 
                "number": 3, 
                "completed_at": "2020-11-16T15:39:00.000Z", 
                "started_at": "2020-11-16T15:39:00.000Z", 
                "conclusion": "success"
            }, 
            {
                "status": "completed", 
                "name": "Set up Python environment variable (Unix)", 
                "number": 4, 
                "completed_at": "2020-11-16T15:39:00.000Z", 
                "started_at": "2020-11-16T15:39:00.000Z", 
                "conclusion": "success"
            }, 
            {
                "status": "completed", 
                "name": "Set up Python environment variable (Windows)", 
                "number": 5, 
                "completed_at": "2020-11-16T15:39:00.000Z", 
                "started_at": "2020-11-16T15:39:00.000Z", 
                "conclusion": "skipped"
            }, 
            {
                "status": "completed", 
                "name": "Extract branch name", 
                "number": 6, 
                "completed_at": "2020-11-16T15:39:00.000Z", 
                "started_at": "2020-11-16T15:39:00.000Z", 
                "conclusion": "success"
            }, 
            {
                "status": "completed", 
                "name": "Upgrade pip", 
                "number": 7, 
                "completed_at": "2020-11-16T15:39:03.000Z", 
                "started_at": "2020-11-16T15:39:00.000Z", 
                "conclusion": "success"
            }, 
            {
                "status": "completed", 
                "name": "Build on Unix", 
                "number": 8, 
                "completed_at": "2020-11-16T15:45:35.000Z", 
                "started_at": "2020-11-16T15:39:03.000Z", 
                "conclusion": "success"
            }, 
            {
                "status": "completed", 
                "name": "Build on Windows", 
                "number": 9, 
                "completed_at": "2020-11-16T15:45:35.000Z", 
                "started_at": "2020-11-16T15:45:35.000Z", 
                "conclusion": "skipped"
            }, 
            {
                "status": "completed", 
                "name": "Post Git checkout with submodules", 
                "number": 18, 
                "completed_at": "2020-11-16T15:45:35.000Z", 
                "started_at": "2020-11-16T15:45:35.000Z", 
                "conclusion": "success"
            }, 
            {
                "status": "completed", 
                "name": "Complete job", 
                "number": 19, 
                "completed_at": "2020-11-16T15:45:35.000Z", 
                "started_at": "2020-11-16T15:45:35.000Z", 
                "conclusion": "success"
            }
        ], 
        "head_sha": "cb2908e961e5f42a333c1f982132d83665d70b5b", 
        "started_at": "2020-11-16T15:38:53Z", 
        "id": 1407196179, 
        "conclusion": "success"
    }, 
    {
        "status": "completed", 
        "check_run_url": "https://api.github.com/repos/cpp-pm/hunter/check-runs/1407196208", 
        "name": "filament osx-10-15-cxx17 macos-10.15", 
        "run_id": 362807396, 
        "url": "https://api.github.com/repos/cpp-pm/hunter/actions/jobs/1407196208", 
        "html_url": "https://github.com/cpp-pm/hunter/runs/1407196208", 
        "completed_at": "2020-11-16T16:54:27Z", 
        "run_url": "https://api.github.com/repos/cpp-pm/hunter/actions/runs/362807396", 
        "node_id": "MDg6Q2hlY2tSdW4xNDA3MTk2MjA4", 
        "steps": [
            {
                "status": "completed", 
                "name": "Set up job", 
                "number": 1, 
                "completed_at": "2020-11-16T15:39:05.000Z", 
                "started_at": "2020-11-16T15:39:03.000Z", 
                "conclusion": "success"
            }, 
            {
                "status": "completed", 
                "name": "Git checkout with submodules", 
                "number": 2, 
                "completed_at": "2020-11-16T15:39:10.000Z", 
                "started_at": "2020-11-16T15:39:05.000Z", 
                "conclusion": "success"
            }, 
            {
                "status": "completed", 
                "name": "Set up Python", 
                "number": 3, 
                "completed_at": "2020-11-16T15:39:11.000Z", 
                "started_at": "2020-11-16T15:39:10.000Z", 
                "conclusion": "success"
            }, 
            {
                "status": "completed", 
                "name": "Set up Python environment variable (Unix)", 
                "number": 4, 
                "completed_at": "2020-11-16T15:39:11.000Z", 
                "started_at": "2020-11-16T15:39:11.000Z", 
                "conclusion": "success"
            }, 
            {
                "status": "completed", 
                "name": "Set up Python environment variable (Windows)", 
                "number": 5, 
                "completed_at": "2020-11-16T15:39:11.000Z", 
                "started_at": "2020-11-16T15:39:11.000Z", 
                "conclusion": "skipped"
            }, 
            {
                "status": "completed", 
                "name": "Extract branch name", 
                "number": 6, 
                "completed_at": "2020-11-16T15:39:11.000Z", 
                "started_at": "2020-11-16T15:39:11.000Z", 
                "conclusion": "success"
            }, 
            {
                "status": "completed", 
                "name": "Upgrade pip", 
                "number": 7, 
                "completed_at": "2020-11-16T15:39:12.000Z", 
                "started_at": "2020-11-16T15:39:11.000Z", 
                "conclusion": "success"
            }, 
            {
                "status": "completed", 
                "name": "Build on Unix", 
                "number": 8, 
                "completed_at": "2020-11-16T16:54:26.000Z", 
                "started_at": "2020-11-16T15:39:12.000Z", 
                "conclusion": "success"
            }, 
            {
                "status": "completed", 
                "name": "Build on Windows", 
                "number": 9, 
                "completed_at": "2020-11-16T16:54:26.000Z", 
                "started_at": "2020-11-16T16:54:26.000Z", 
                "conclusion": "skipped"
            }, 
            {
                "status": "completed", 
                "name": "Post Git checkout with submodules", 
                "number": 18, 
                "completed_at": "2020-11-16T16:54:26.000Z", 
                "started_at": "2020-11-16T16:54:26.000Z", 
                "conclusion": "success"
            }, 
            {
                "status": "completed", 
                "name": "Complete job", 
                "number": 19, 
                "completed_at": "2020-11-16T16:54:27.000Z", 
                "started_at": "2020-11-16T16:54:26.000Z", 
                "conclusion": "success"
            }
        ], 
        "head_sha": "cb2908e961e5f42a333c1f982132d83665d70b5b", 
        "started_at": "2020-11-16T15:39:03Z", 
        "id": 1407196208, 
        "conclusion": "success"
    }, 
    {
        "status": "completed", 
        "check_run_url": "https://api.github.com/repos/cpp-pm/hunter/check-runs/1407196237", 
        "name": "filament vs-16-2019-win64-cxx17 windows-2019", 
        "run_id": 362807396, 
        "url": "https://api.github.com/repos/cpp-pm/hunter/actions/jobs/1407196237", 
        "html_url": "https://github.com/cpp-pm/hunter/runs/1407196237", 
        "completed_at": "2020-11-16T15:47:03Z", 
        "run_url": "https://api.github.com/repos/cpp-pm/hunter/actions/runs/362807396", 
        "node_id": "MDg6Q2hlY2tSdW4xNDA3MTk2MjM3", 
        "steps": [
            {
                "status": "completed", 
                "name": "Set up job", 
                "number": 1, 
                "completed_at": "2020-11-16T15:38:58.000Z", 
                "started_at": "2020-11-16T15:38:57.000Z", 
                "conclusion": "success"
            }, 
            {
                "status": "completed", 
                "name": "Git checkout with submodules", 
                "number": 2, 
                "completed_at": "2020-11-16T15:39:17.000Z", 
                "started_at": "2020-11-16T15:38:58.000Z", 
                "conclusion": "success"
            }, 
            {
                "status": "completed", 
                "name": "Set up Python", 
                "number": 3, 
                "completed_at": "2020-11-16T15:39:17.000Z", 
                "started_at": "2020-11-16T15:39:17.000Z", 
                "conclusion": "success"
            }, 
            {
                "status": "completed", 
                "name": "Set up Python environment variable (Unix)", 
                "number": 4, 
                "completed_at": "2020-11-16T15:39:17.000Z", 
                "started_at": "2020-11-16T15:39:17.000Z", 
                "conclusion": "skipped"
            }, 
            {
                "status": "completed", 
                "name": "Set up Python environment variable (Windows)", 
                "number": 5, 
                "completed_at": "2020-11-16T15:39:29.000Z", 
                "started_at": "2020-11-16T15:39:17.000Z", 
                "conclusion": "success"
            }, 
            {
                "status": "completed", 
                "name": "Extract branch name", 
                "number": 6, 
                "completed_at": "2020-11-16T15:39:29.000Z", 
                "started_at": "2020-11-16T15:39:29.000Z", 
                "conclusion": "success"
            }, 
            {
                "status": "completed", 
                "name": "Upgrade pip", 
                "number": 7, 
                "completed_at": "2020-11-16T15:39:36.000Z", 
                "started_at": "2020-11-16T15:39:29.000Z", 
                "conclusion": "success"
            }, 
            {
                "status": "completed", 
                "name": "Build on Unix", 
                "number": 8, 
                "completed_at": "2020-11-16T15:39:36.000Z", 
                "started_at": "2020-11-16T15:39:36.000Z", 
                "conclusion": "skipped"
            }, 
            {
                "status": "completed", 
                "name": "Build on Windows", 
                "number": 9, 
                "completed_at": "2020-11-16T15:46:59.000Z", 
                "started_at": "2020-11-16T15:39:36.000Z", 
                "conclusion": "success"
            }, 
            {
                "status": "completed", 
                "name": "Post Git checkout with submodules", 
                "number": 18, 
                "completed_at": "2020-11-16T15:47:03.000Z", 
                "started_at": "2020-11-16T15:46:59.000Z", 
                "conclusion": "success"
            }, 
            {
                "status": "completed", 
                "name": "Complete job", 
                "number": 19, 
                "completed_at": "2020-11-16T15:47:03.000Z", 
                "started_at": "2020-11-16T15:47:03.000Z", 
                "conclusion": "success"
            }
        ], 
        "head_sha": "cb2908e961e5f42a333c1f982132d83665d70b5b", 
        "started_at": "2020-11-16T15:38:57Z", 
        "id": 1407196237, 
        "conclusion": "success"
    }
]